jytestrun.py
jytestrunopt1-0.0.1.dist-info/METADATA
jytestrunopt1-0.0.1.dist-info/WHEEL
jytestrunopt1-0.0.1.dist-info/top_level.txt
jytestrunopt1-0.0.1.dist-info/RECORD
