Metadata-Version: 2.1
Name: jytestrunopt1
Version: 0.0.1
Summary: opt1
Home-page: https://www.cnblogs.com/zhangjialu2015/p/5173313.html
Author: zjy
Author-email: unknown@bgsn.com
License: UNKNOWN
Platform: UNKNOWN
